kosher_cli/__init__.py
kosher_cli/main.py
kosher_cli/shell.py
kosher_cli/ctr/__init__.py
kosher_cli/ctr/container.py
kosher_cli/ctr/node.py
kosher_cli/ctr/python.py
kosher_cli/ctr/ruby.py
kosher_cli-0.0.3.dist-info/LICENSE
kosher_cli-0.0.3.dist-info/METADATA
kosher_cli-0.0.3.dist-info/WHEEL
kosher_cli-0.0.3.dist-info/entry_points.txt
kosher_cli-0.0.3.dist-info/top_level.txt
kosher_cli-0.0.3.dist-info/RECORD
