Metadata-Version: 2.2
Name: kosher-cli
Version: 0.0.3
Summary: Kosher - Language Environment Manager
Home-page: https://github.com/voidisnull/kosher
Author: Saksham
Author-email: voidisnull@duck.com
Classifier: Programming Language :: Python :: 3
Classifier: License :: OSI Approved :: MIT License
Classifier: Operating System :: OS Independent
Requires-Python: >=3.10
License-File: LICENSE
Requires-Dist: docker>=7.0.0
Requires-Dist: rich>=13.0.0
Dynamic: author
Dynamic: author-email
Dynamic: classifier
Dynamic: home-page
Dynamic: requires-dist
Dynamic: requires-python
Dynamic: summary
